cxe_test_frameworks/__init__.py
cxe_test_frameworks/api/__init__.py
cxe_test_frameworks/api/client.py
cxe_test_frameworks/api/constants.py
cxe_test_frameworks/api/fixtures.py
cxe_test_frameworks/api/validators.py
cxe_test_frameworks/ui/__init__.py
cxe_test_frameworks/ui/assertions.py
cxe_test_frameworks/ui/base_element.py
cxe_test_frameworks/ui/base_page.py
cxe_test_frameworks/ui/waits.py
cxe_test_frameworks/utils/__init__.py
cxe_test_frameworks/utils/configurations.py
cxe_test_frameworks/utils/logger.py
cxe_test_frameworks-0.2.1.dist-info/METADATA
cxe_test_frameworks-0.2.1.dist-info/WHEEL
cxe_test_frameworks-0.2.1.dist-info/top_level.txt
cxe_test_frameworks-0.2.1.dist-info/RECORD
