Metadata-Version: 2.4
Name: cxe-test-frameworks
Version: 0.2.1
Summary: Shared testing infrastructure for CXE services (API + UI)
Author-email: CXE Team <cxe-team@snowflake.com>
License: Proprietary
Requires-Python: >=3.11
Requires-Dist: pytest>=7.4.0
Requires-Dist: allure-pytest>=2.13.0
Requires-Dist: requests>=2.31.0
Requires-Dist: playwright>=1.40.0
Requires-Dist: snowflake-connector-python>=3.0.0
Requires-Dist: structlog>=23.0.0
Requires-Dist: colorlog>=6.0.0
Requires-Dist: python-dotenv>=1.0.0
Provides-Extra: dev
Requires-Dist: pytest-cov>=4.1.0; extra == "dev"
Requires-Dist: pytest-mock>=3.12.0; extra == "dev"
Requires-Dist: black>=23.0.0; extra == "dev"
Requires-Dist: mypy>=1.0.0; extra == "dev"
Requires-Dist: flake8>=7.0.0; extra == "dev"
